netqr/__init__.py
netqr/netqr.py
netqr/py.typed
netqr/util_log.py
netqr-0.1.1.data/scripts/qr.py
netqr-0.1.1.dist-info/METADATA
netqr-0.1.1.dist-info/WHEEL
netqr-0.1.1.dist-info/top_level.txt
netqr-0.1.1.dist-info/RECORD
