Metadata-Version: 2.1
Name: netqr
Version: 0.1.1
Summary: Rich Tong's Fine QR Utilities
Home-page: https://github.com/netdrones/qr
Author: Richard Tong
Author-email: rich@netdron.es
License: UNKNOWN
Project-URL: Bug Tracker, https://github.com/netdrones/qr/issues
Platform: UNKNOWN
Classifier: Programming Language :: Python :: 3
Classifier: Programming Language :: Python :: 3.8
Classifier: License :: OSI Approved :: MIT License
Classifier: Operating System :: OS Independent
Requires-Python: >=3.8
